ide_gen/__init__.py
ide_gen/visual_studio2003.py
ide_gen-0.1.0.dist-info/licenses/LICENSE.txt
ide_gen-0.1.0.dist-info/METADATA
ide_gen-0.1.0.dist-info/WHEEL
ide_gen-0.1.0.dist-info/top_level.txt
ide_gen-0.1.0.dist-info/RECORD
