Metadata-Version: 2.4
Name: ide_gen
Version: 0.1.0
Summary: IDE Project Generator.
Home-page: https://github.com/burgerbecky/ide-gen
Author: Rebecca Ann Heineman
Author-email: becky@burgerbecky.com
License-Expression: MIT
Project-URL: Homepage, https://github.com/burgerbecky/ide-gen
Project-URL: Documentation, https://ide-gen.readthedocs.io/en/latest/
Project-URL: Source, https://github.com/burgerbecky/ide-gen
Keywords: burger,perforce,burgerlib,development,python,windows
Platform: Any
Classifier: Development Status :: 5 - Production/Stable
Classifier: Environment :: Console
Classifier: Intended Audience :: Developers
Classifier: Topic :: Software Development
Classifier: Topic :: Software Development :: Build Tools
Classifier: Operating System :: OS Independent
Classifier: Natural Language :: English
Classifier: Programming Language :: Python
Classifier: Programming Language :: Python :: 2
Classifier: Programming Language :: Python :: 2.7
Classifier: Programming Language :: Python :: 3
Classifier: Programming Language :: Python :: 3.4
Classifier: Programming Language :: Python :: 3.5
Classifier: Programming Language :: Python :: 3.6
Classifier: Programming Language :: Python :: 3.7
Classifier: Programming Language :: Python :: 3.8
Classifier: Programming Language :: Python :: 3.9
Classifier: Programming Language :: Python :: 3.10
Classifier: Programming Language :: Python :: 3.11
Classifier: Programming Language :: Python :: 3.12
Classifier: Programming Language :: Python :: 3.13
Requires-Python: >=2.7,!=3.0.*,!=3.1.*,!=3.2.*,!=3.3.*
License-File: LICENSE.txt
Requires-Dist: setuptools>=44.0.0
Requires-Dist: burger>=1.5
Dynamic: home-page
Dynamic: license-file
Dynamic: requires-python
